mixt/__init__.py
mixt/element.py
mixt/exceptions.py
mixt/html.py
mixt/proptypes.py
mixt/codec/__init__.py
mixt/codec/fast_register.py
mixt/codec/html_tokenizer.py
mixt/codec/parser.py
mixt/codec/pytokenize.py
mixt/codec/register.py
mixt/codec/state.py
mixt/codec/tokenizer.py
mixt/contrib/__init__.py
mixt/contrib/css/__init__.py
mixt/contrib/css/css_keywords_list.py
mixt/contrib/css/loading.py
mixt/contrib/css/modes.py
mixt/contrib/css/rendering.py
mixt/contrib/css/units.py
mixt/contrib/css/utils.py
mixt/contrib/css/vars.py
mixt/examples/__init__.py
mixt/examples/simple.py
mixt/examples/simple_pure_python.py
mixt/examples/user_guide/__init__.py
mixt/examples/user_guide/__main__.py
mixt/examples/user_guide/mixt.py
mixt/examples/user_guide/pure_python.py
mixt/internal/__init__.py
mixt/internal/base.py
mixt/internal/collectors.py
mixt/internal/dev_mode.py
mixt/internal/html.py
mixt/internal/proptypes.py
mixt/misc/__init__.py
mixt/misc/pylint_no_mixt_encoding_checker.py
mixt/scripts/__init__.py
mixt/scripts/mixt_post_install.py
mixt/scripts/parse_file.py
mixt/scripts/run_file.py
mixt/vendor/__init__.py
mixt/vendor/pytypes/__init__.py
mixt/vendor/pytypes/exceptions.py
mixt/vendor/pytypes/stubfile_2_converter.py
mixt/vendor/pytypes/stubfile_manager.py
mixt/vendor/pytypes/type_util.py
mixt/vendor/pytypes/typechecker.py
mixt/vendor/pytypes/typecomment_parser.py
mixt/vendor/pytypes/typelogger.py
mixt/vendor/pytypes/util.py
mixt-1.2.3.dist-info/LICENSE
mixt-1.2.3.dist-info/METADATA
mixt-1.2.3.dist-info/WHEEL
mixt-1.2.3.dist-info/entry_points.txt
mixt-1.2.3.dist-info/top_level.txt
mixt-1.2.3.dist-info/zip-safe
mixt-1.2.3.dist-info/RECORD
