Metadata-Version: 2.1
Name: mixt
Version: 1.2.3
Summary: Write html components directly in python and you have a beautiful but controversial MIXTure
Home-page: https://github.com/twidi/mixt
Author: Stéphane "Twidi" Angel
Author-email: s.angel@twidi.com
License: MIT
Keywords: python,html,components,templating,web-components,react-style
Platform: UNKNOWN
Classifier: Development Status :: 5 - Production/Stable
Classifier: License :: OSI Approved :: MIT License
Classifier: Programming Language :: Python
Classifier: Programming Language :: Python :: 3
Classifier: Programming Language :: Python :: 3.6
Classifier: Programming Language :: Python :: 3.7
Classifier: Programming Language :: Python :: 3.8
Classifier: Programming Language :: Python :: 3 :: Only
Requires-Dist: wrapt
Provides-Extra: dev
Requires-Dist: black ; extra == 'dev'
Requires-Dist: factory-boy ; extra == 'dev'
Requires-Dist: flake8 ; extra == 'dev'
Requires-Dist: flake8-bugbear ; extra == 'dev'
Requires-Dist: flake8-comprehensions ; extra == 'dev'
Requires-Dist: flake8-docstrings ; extra == 'dev'
Requires-Dist: flake8-formatter-abspath ; extra == 'dev'
Requires-Dist: flake8-imports ; extra == 'dev'
Requires-Dist: flake8-pep3101 ; extra == 'dev'
Requires-Dist: ipython ; extra == 'dev'
Requires-Dist: isort ; extra == 'dev'
Requires-Dist: mypy ; extra == 'dev'
Requires-Dist: patchy ; extra == 'dev'
Requires-Dist: pycodestyle ; extra == 'dev'
Requires-Dist: pydocstyle ; extra == 'dev'
Requires-Dist: pylint ; extra == 'dev'
Requires-Dist: pytest ; extra == 'dev'
Requires-Dist: twine ; extra == 'dev'
Requires-Dist: wheel ; extra == 'dev'
Provides-Extra: doc
Requires-Dist: bottle ; extra == 'doc'
Requires-Dist: inspect-mate ; extra == 'doc'
Requires-Dist: numpydoc ; extra == 'doc'
Requires-Dist: pygments ; extra == 'doc'
Requires-Dist: python-slugify ; extra == 'doc'
Provides-Extra: test
Requires-Dist: factory-boy ; extra == 'test'
Requires-Dist: pytest ; extra == 'test'
